pyg_mongo_async/__init__.py
pyg_mongo_async/_async_cursor.py
pyg_mongo_async/_async_reader.py
pyg_mongo_async/_db_acell.py
pyg_mongo_async-0.0.1.dist-info/LICENSE
pyg_mongo_async-0.0.1.dist-info/METADATA
pyg_mongo_async-0.0.1.dist-info/WHEEL
pyg_mongo_async-0.0.1.dist-info/top_level.txt
pyg_mongo_async-0.0.1.dist-info/RECORD
