Metadata-Version: 2.1
Name: pyg-mongo-async
Version: 0.0.1
Summary: Utilities for data manipulation including creation of DAGs and tables
Home-page: https://github.com/gityoav/pyg-mongo-async
Author: Yoav Git
Author-email: yoav.git@gmail.com
License: UNKNOWN
Project-URL: Bug Tracker, https://github.com/gityoav/pyg-mongo-async/issues
Platform: UNKNOWN
Classifier: Programming Language :: Python :: 3
Classifier: License :: OSI Approved :: MIT License
Classifier: Operating System :: OS Independent
Requires-Python: >=3.6
License-File: LICENSE
Requires-Dist: pyg-mongo
Requires-Dist: motor
